Metadata-Version: 2.1
Name: chromedriver-binary
Version: 76.0.3809.25.0
Summary: Installer for chromedriver.
Home-page: https://github.com/danielkaiser/python-chromedriver-binary
Author: Daniel Kaiser
Author-email: daniel.kaiser94@gmail.com
License: MIT
Keywords: chromedriver chrome browser selenium splinter
Platform: UNKNOWN
Classifier: Development Status :: 5 - Production/Stable
Classifier: Topic :: Software Development :: Testing
Classifier: Topic :: System :: Installation/Setup
Classifier: Topic :: Software Development :: Libraries :: Python Modules
Classifier: License :: OSI Approved :: MIT License
